auth0_auth/__init__.py
auth0_auth/backends.py
auth0_auth/context_processors.py
auth0_auth/urls.py
auth0_auth/utils.py
auth0_auth/views.py
django_auth0_auth-3.0.1.dist-info/METADATA
django_auth0_auth-3.0.1.dist-info/RECORD
django_auth0_auth-3.0.1.dist-info/WHEEL
django_auth0_auth-3.0.1.dist-info/top_level.txt
