Metadata-Version: 2.1
Name: django-auth0-auth
Version: 3.0.1
Summary: Authenticated users using Auth0.
Home-page: https://bitbucket.org/megaman821/django-auth0-auth
Author: Jason Christa
Author-email: jason@zeitcode.com
License: UNKNOWN
Platform: UNKNOWN
Classifier: Environment :: Web Environment
Classifier: License :: OSI Approved :: BSD License
Classifier: Framework :: Django
Classifier: Programming Language :: Python
Requires-Dist: Django (>=1.4)
Requires-Dist: PyJWT (>=1.1.0)
Requires-Dist: requests (>=2.0.0)
